EMPeaks/__init__.py
EMPeaks/file_io.py
EMPeaks/Background/__init__.py
EMPeaks/Background/_background.py
EMPeaks/DoniachSunjicMixture/__init__.py
EMPeaks/DoniachSunjicMixture/_doniachsunjic.py
EMPeaks/DoniachSunjicMixture/_dsmm.py
EMPeaks/GaussianMixture/__init__.py
EMPeaks/GaussianMixture/_em.py
EMPeaks/GaussianMixture/_gaussian.py
EMPeaks/GaussianMixture/_gmm.py
EMPeaks/GaussianMixture/_gmm2.py
EMPeaks/GaussianMixture/_spectrum_adapted_em.py
EMPeaks/GaussianMixture/Tests/__init__.py
EMPeaks/GaussianMixture/Tests/_test_data 2.py
EMPeaks/GaussianMixture/Tests/_test_data.py
EMPeaks/GaussianMixture/Tests/_test_em 2.py
EMPeaks/GaussianMixture/Tests/_test_em.py
EMPeaks/GaussianMixture/Tests/_test_exp_data 2.py
EMPeaks/GaussianMixture/Tests/_test_exp_data.py
EMPeaks/GaussianMixture/Tests/_test_sepctrum_adapted_em 2.py
EMPeaks/GaussianMixture/Tests/_test_sepctrum_adapted_em.py
EMPeaks/LorentzianMixture/__init__.py
EMPeaks/LorentzianMixture/_lmm.py
EMPeaks/LorentzianMixture/_lorentz.py
EMPeaks/PseudoVoigtMixture/__init__.py
EMPeaks/PseudoVoigtMixture/_pseudo_voigt.py
EMPeaks/PseudoVoigtMixture/_pvmm.py
EMPeaks-2.1.0.dist-info/LICENSE
EMPeaks-2.1.0.dist-info/METADATA
EMPeaks-2.1.0.dist-info/WHEEL
EMPeaks-2.1.0.dist-info/top_level.txt
EMPeaks-2.1.0.dist-info/RECORD
