Metadata-Version: 2.1
Name: EMPeaks
Version: 2.1.0
Summary: 'high-throughput spectrum peak modeling tools by using Spectrum adapted EM algorithms'
Author: Yasunobu Ando
Author-email: yasunobu.ando@aist.go.jp
Classifier: Programming Language :: Python :: 3
Classifier: License :: OSI Approved :: BSD License
Classifier: Operating System :: OS Independent
Requires-Python: >=3.8
License-File: LICENSE
